camphr_transformers/VERSION.py
camphr_transformers/__init__.py
camphr_transformers/ner.py
camphr_transformers-0.1.5.dist-info/WHEEL
camphr_transformers-0.1.5.dist-info/METADATA
camphr_transformers-0.1.5.dist-info/RECORD
