Metadata-Version: 2.1
Name: camphr-transformers
Version: 0.1.5
Summary: 
Author: Yohei Tamura
Author-email: tamuhey@gmail.com
Requires-Python: >=3.7,<4.0
Classifier: Programming Language :: Python :: 3
Classifier: Programming Language :: Python :: 3.7
Classifier: Programming Language :: Python :: 3.8
Classifier: Programming Language :: Python :: 3.9
Provides-Extra: torch
Requires-Dist: camphr (>=0.10.0,<0.11.0)
Requires-Dist: pytextspan (>=0.5.4,<0.6.0)
Requires-Dist: torch (>=1.8.0,<2.0.0); extra == "torch"
Requires-Dist: transformers (>=4.8,<5.0)
